{
  "bms0": {
    "bms_basic_info": {
      "battery_pack_id": "PSNIOAD1100B599999CE6000A10TEST",
      "gb_battery_pack_id": "001PEAEM222222BCV030test",
      "bms_software_ver": "P0208587 CG",
      "bms_hardware_ver": "P0208909 AB",
      "bms_protocal_version": "2.0.1"
    },
    "bms_realtime_info": {
      "bms_pack_voltage": "350",
      "bms_soc": "38",
      "bms_ess_inlet_temp": "22.75",
      "bms_estimate_chrg_time": "0",
      "bms_pack_crrnt": "0",
      "bms_customer_usage_soc": "36",
      "bms_ess_outlet_temp": "22.375",
      "bms_insolation_resistance_value": "50000",
      "bms_pack_energy_available": "0",
      "bms_high_resl_soc": "20",
      "bms_dc_chrg_voltage_req": "443.7",
      "bms_dc_chrg_current_req": "-228.1",
      "bms_chrg_current_limit": "-369.6",
      "bms_cell_voltg_max": "3.648",
      "bms_maximum_cell_voltage_number": "90",
      "bms_cell_voltg_min": "3.645",
      "bms_minimum_cell_voltage_number": "83",
      "bms_cell_voltg_average": "3.646",
      "bms_temp_max": "17.5",
      "bms_maximum_temp_number": "37",
      "bms_temp_min": "16.5",
      "bms_minimum_temp_number": "32",
      "bms_temp_average": "16.5",
      "bms_cell_voltg_max_b": "3.647",
      "bms_max_cell_voltg_num_b": "1",
      "bms_cell_voltg_min_b": "3.646",
      "bms_min_cell_voltg_num_b": "2",
      "bms_temp_max_b": "21.5",
      "bms_max_temp_num_b": "1",
      "bms_temp_min_b": "21",
      "bms_min_temp_num_b": "10",
      "bms_chrg_power_limit_lt": "93.3",
      "bms_dischrg_power_limit_lt": "152.7",
      "bms_chrg_power_limit_st": "145.9",
      "bms_dischrg_power_limit_st": "653.9",
      "bms_chrg_power_limit_dynamic": "145.9",
      "bms_dischrg_power_limit_dynamic": "653.9"
    },
    "bms_config_info": {
      "bms_battery_type": "6",
      "maximum_charging_current": "-350",
      "bms_battery_rated_capacity": "0",
      "bms_battery_pack_cap": "6",
      "maximum_charging_voltage": "417.6",
      "bms_battery_rated_voltage": "0",
      "bms_dc_chrg_final_soc": "99",
      "maximum_permit_charge_cell_volt": "0",
      "bms_voltage_limit_max": "408",
      "maximum_permit_temp": "57",
      "battery_normal_capacity": "100.3",
      "bms_voltage_limit_min": "0",
      "bms_max_permit_dc_charge_voltage": "0"
    },
    "bms_status_info": {
      "bms_fault_lvl": "0",
      "soc_jump_reason": "0",
      "reflash_req": "0",
      "bms_isolation_lvl": "0",
      "bms_if_bms_soc_set": "0",
      "bms_inhibit_cls_reason": "0",
      "bms_charge_available": "1",
      "bms_soc_over_under": "0",
      "bms_contactor_states": "0",
      "bms_ready_dc_charging": "0",
      "bms_if_pack_voltage_set": "0",
      "bms_abort_cls_reason": "0",
      "battery_output_connector_state": "0",
      "bms_charge_state": "1",
      "bms_lock_state": "0",
      "bms_balance_sts": "0",
      "bms_inter_lock_sts": "0",
      "bms_sts": "0",
      "bms_hv_shutdown_req": "0",
      "bms_dc_chrg_derate_crrnt_sts": "0",
      "bms_ac_test_status": "0",
      "bms_dc_chrg_mode": "0",
      "bms_fault_cat": "0",
      "dc_charging_permit_status": "1",
      "bms_if_cell_voltage_set": "0",
      "bms_full_chrg_flg": "0",
      "bms_pack_therm_out_of_ctrl_vld": "0",
      "bms_pack_iso_dec_sts": "0",
      "bms_cel_slf_dchrg_sts": "0",
      "bms_cell_tar_temp_mode_req_A": "0",
      "bms_over_dc_chrg_protect": "0",
      "bms_cell_tar_temp": "0",
      "bms_cell_tar_temp_validity": "0",
      "iso_ins_decrease_warning": "0"
    },
    "bms_alarm_info": {
      "bms_pack_over_temp": "0",
      "bms_connector_over_temp": "0",
      "bms_hv_conector_error": "0",
      "bms_chrg_conn_over_temp": "0",
      "bms_chrg_conn_error": "0",
      "bms_hv_isolation": "0",
      "bms_over_current": "0",
      "bms_other_error": "0",
      "battery_cell_vol_high_alarm": "0",
      "battery_cell_vol_low_alarm": "0",
      "battery_pck_volt_over_alarm": "0",
      "battery_pck_volt_under_alarm": "0",
      "battery_temp_differ_alarm": "0",
      "battery_cell_temp_high_alarm": "0",
      "battery_cell_temp_low_alarm": "0",
      "battery_type_dismatch_alarm": "0",
      "battery_consistency_alarm": "0",
      "bms_inhibit_chrg_flt": "0",
      "bms_pack_therm_out_of_ctrl_alrm": "0",
      "battery_abnormal_alarm1": "0",
      "battery_abnormal_alarm2": "0",
      "battery_abnormal_alarm3": "0",
      "battery_abnormal_alarm4": "0",
      "bms_cell_voltage_over_under": "0",
      "battery_temp_over": "0",
      "bms_pack_under_temp": "0",
      "bms_dc_chrg_curr_over": "0",
      "bms_voltg_mismatch": "0"
    },
    "bms_volt_info": {
      "N1": "3.647",
      "N2": "3.647",
      "N3": "3.646",
      "N4": "3.647",
      "N5": "3.647",
      "N6": "3.647",
      "N7": "3.647",
      "N8": "3.647",
      "N9": "3.646",
      "N10": "3.646",
      "N11": "3.647",
      "N12": "3.647",
      "N13": "3.645",
      "N14": "3.648",
      "N15": "3.647",
      "N16": "3.646",
      "N17": "3.647",
      "N18": "3.647",
      "N19": "3.645",
      "N20": "3.647",
      "N21": "3.648",
      "N22": "3.647",
      "N23": "3.646",
      "N24": "3.647",
      "N25": "3.646",
      "N26": "3.646",
      "N27": "3.646",
      "N28": "3.646",
      "N29": "3.646",
      "N30": "3.647",
      "N31": "3.648",
      "N32": "3.647",
      "N33": "3.647",
      "N34": "3.647",
      "N35": "3.647",
      "N36": "3.647",
      "N37": "3.647",
      "N38": "3.647",
      "N39": "3.647",
      "N40": "3.647",
      "N41": "3.647",
      "N42": "3.647",
      "N43": "3.647",
      "N44": "3.647",
      "N45": "3.647",
      "N46": "3.647",
      "N47": "3.647",
      "N48": "3.647",
      "N49": "3.647",
      "N50": "3.647",
      "N51": "3.647",
      "N52": "3.647",
      "N53": "3.647",
      "N54": "3.647",
      "N55": "3.647",
      "N56": "3.647",
      "N57": "3.647",
      "N58": "3.647",
      "N59": "3.647",
      "N60": "3.647",
      "N61": "3.647",
      "N62": "3.647",
      "N63": "3.647",
      "N64": "3.647",
      "N65": "3.647",
      "N66": "3.647",
      "N67": "3.647",
      "N68": "3.647",
      "N69": "3.647",
      "N70": "3.647",
      "N71": "3.647",
      "N72": "3.647",
      "N73": "3.647",
      "N74": "3.647",
      "N75": "3.647",
      "N76": "3.647",
      "N77": "3.647",
      "N78": "3.647",
      "N79": "3.647",
      "N80": "3.647",
      "N81": "3.647",
      "N82": "3.647",
      "N83": "3.647",
      "N84": "3.647",
      "N85": "3.647",
      "N86": "3.647",
      "N87": "3.647",
      "N88": "3.647",
      "N89": "3.647",
      "N90": "3.647",
      "N91": "3.647",
      "N92": "3.647",
      "N93": "3.646",
      "N94": "3.646",
      "N95": "3.647",
      "N96": "3.646"
    },
    "bms_temp_info": {
      "T1_A1": "18",
      "T1_A2": "16",
      "T1_B1": "17",
      "T1_B2": "16",
      "T2_A1": "17",
      "T2_A2": "17",
      "T2_B1": "17",
      "T2_B2": "16",
      "T3_A1": "17",
      "T3_A2": "16",
      "T3_B1": "16",
      "T3_B2": "16",
      "T4_A1": "17",
      "T4_A2": "17",
      "T4_B1": "17",
      "T4_B2": "17",
      "T5_A1": "17",
      "T5_A2": "17",
      "T5_B1": "16",
      "T5_B2": "17",
      "T6_A1": "16",
      "T6_A2": "17",
      "T6_B1": "17",
      "T6_B2": "16",
      "T7_A1": "17",
      "T7_A2": "16",
      "T7_B1": "17",
      "T7_B2": "17",
      "T8_A1": "17",
      "T8_A2": "17",
      "T8_B1": "17",
      "T8_B2": "16",
      "T9_A1": "16",
      "T9_A2": "17",
      "T9_B1": "17",
      "T9_B2": "17",
      "T10_A1": "17",
      "T10_A2": "17",
      "T10_B1": "17",
      "T10_B2": "16",
      "T11_A1": "16",
      "T11_A2": "17",
      "T11_B1": "17",
      "T11_B2": "17",
      "T12_A1": "17",
      "T12_A2": "17",
      "T12_B1": "17",
      "T12_B2": "17"
    }
  }
}